ttiny/__init__.py
ttiny/ttiny.py
ttiny/ttiny_7cfg.py
ttiny-0.1.0.dist-info/licenses/LICENSE
ttiny-0.1.0.dist-info/METADATA
ttiny-0.1.0.dist-info/WHEEL
ttiny-0.1.0.dist-info/entry_points.txt
ttiny-0.1.0.dist-info/top_level.txt
ttiny-0.1.0.dist-info/RECORD
