Metadata-Version: 2.4
Name: ttiny
Version: 0.1.0
Summary: ttiny is a lightweight TUI mode-based text editor for files of all kinds
Home-page: https://github.com/yourname/ttiny
Author: displaynameishere
Classifier: Programming Language :: Python :: 3
Classifier: Environment :: Console
Classifier: Operating System :: POSIX :: Linux
Requires-Python: >=3.6
License-File: LICENSE
Dynamic: author
Dynamic: classifier
Dynamic: description
Dynamic: description-content-type
Dynamic: home-page
Dynamic: license-file
Dynamic: requires-python
Dynamic: summary
